blscint/__init__.py
blscint/bounds.py
blscint/dataframe.py
blscint/factors.py
blscint/frame_proc.py
blscint/ne2001.py
blscint/scint_gen.py
blscint/time_series.py
blscint/tscint_sampling.py
blscint-0.0.1.dist-info/METADATA
blscint-0.0.1.dist-info/WHEEL
blscint-0.0.1.dist-info/top_level.txt
blscint-0.0.1.dist-info/RECORD
