Metadata-Version: 2.1
Name: blscint
Version: 0.0.1
Summary: SETI scintillation utilities
Home-page: UNKNOWN
Author: Bryan Brzycki
Author-email: bbrzycki@berkeley.edu
License: UNKNOWN
Platform: UNKNOWN
Classifier: Programming Language :: Python :: 3
Classifier: License :: OSI Approved :: MIT License
Classifier: Operating System :: OS Independent
Requires-Dist: numpy (>=1.18.1)
Requires-Dist: scipy (>=1.4.1)
Requires-Dist: astropy (>=4.0)
Requires-Dist: blimpy (>=2.0.0)
Requires-Dist: setigen (>=2.0.6)
Requires-Dist: matplotlib (>=3.1.3)
Requires-Dist: tqdm (>=4.47.0)
Requires-Dist: sphinx-rtd-theme (>=0.4.3)
